round360/__init__.py
round360/cli.py
round360/round360.py
round360-0.1.0.dist-info/AUTHORS.rst
round360-0.1.0.dist-info/LICENSE
round360-0.1.0.dist-info/METADATA
round360-0.1.0.dist-info/WHEEL
round360-0.1.0.dist-info/entry_points.txt
round360-0.1.0.dist-info/top_level.txt
round360-0.1.0.dist-info/RECORD
