Metadata-Version: 2.1
Name: round360
Version: 0.1.0
Summary: This repo is for processing data from the Samsung 360 Round camera.
Home-page: https://github.com/JohnKoenig0375/round360
Author: John Koenig
Author-email: JohnKoenig0375@gmail.com
License: MIT license
Keywords: round360
Platform: UNKNOWN
Classifier: Development Status :: 2 - Pre-Alpha
Classifier: Intended Audience :: Developers
Classifier: License :: OSI Approved :: MIT License
Classifier: Natural Language :: English
Classifier: Programming Language :: Python :: 2
Classifier: Programming Language :: Python :: 2.7
Classifier: Programming Language :: Python :: 3
Classifier: Programming Language :: Python :: 3.4
Classifier: Programming Language :: Python :: 3.5
Classifier: Programming Language :: Python :: 3.6
Classifier: Programming Language :: Python :: 3.7
Requires-Dist: Click (>=6.0)
Requires-Dist: OpenCV-python
